odoo_autodiscover/__init__.py
odoo_autodiscover/monkey.py
odoo_autodiscover/odoo_gevent_autodiscover.py
odoo_autodiscover/odoo_server_autodiscover.py
odoo_autodiscover-1.0.3.data/scripts/odoo-autodiscover.py
odoo_autodiscover-1.0.3.dist-info/DESCRIPTION.rst
odoo_autodiscover-1.0.3.dist-info/METADATA
odoo_autodiscover-1.0.3.dist-info/RECORD
odoo_autodiscover-1.0.3.dist-info/WHEEL
odoo_autodiscover-1.0.3.dist-info/entry_points.txt
odoo_autodiscover-1.0.3.dist-info/metadata.json
odoo_autodiscover-1.0.3.dist-info/top_level.txt
