Metadata-Version: 2.0
Name: odoo-autodiscover
Version: 1.0.3
Summary: An Odoo launcher that discovers addons automatically
Home-page: http://github.com/acsone/odoo-autodiscover
Author: ACSONE SA/NV
Author-email: info@acsone.eu
License: LGPLv3
Platform: UNKNOWN
Classifier: Development Status :: 5 - Production/Stable
Classifier: Intended Audience :: Developers
Classifier: License :: OSI Approved :: GNU Lesser General Public License v3 (LGPLv3)
Classifier: Operating System :: OS Independent
Classifier: Programming Language :: Python :: 2.7
Requires-Dist: odoo (<9.1a,>=8.0a)
